{"imageSize":{"w":556,"h":315},"slots":[{"index":0,"box":{"left":162,"top":74,"width":37,"height":54},"aHash64":"c190c087878785c7","dHash64":"76d9edf2f2f2f2f0","pHash64":"2a4c6b2aa272f9ea","autoDetected":false,"candidates":[]},{"index":1,"box":{"left":199,"top":74,"width":37,"height":54},"aHash64":"38000000fffffff0","dHash64":"9c02e6e6664c1a7c","pHash64":"480f4f8d4b8f49c7","autoDetected":false,"candidates":[]},{"index":2,"box":{"left":237,"top":74,"width":37,"height":54},"aHash64":"00000008f6f6f67a","dHash64":"56230ec59933311d","pHash64":"47380de699734ace","autoDetected":false,"candidates":[]},{"index":3,"box":{"left":275,"top":74,"width":37,"height":54},"aHash64":"000000fdffff0f1f","dHash64":"bafc9b9404c48803","pHash64":"2b5634abd22f56c4","autoDetected":false,"candidates":[]},{"index":4,"box":{"left":313,"top":74,"width":37,"height":54},"aHash64":"00000070fffff8b1","dHash64":"f326a11a5961ff9a","pHash64":"46107eb5c674373c","autoDetected":false,"candidates":[]},{"index":5,"box":{"left":351,"top":74,"width":37,"height":54},"aHash64":"000000b0ff7fffff","dHash64":"30d36999531250d0","pHash64":"265d7b86cf0b1b30","autoDetected":false,"candidates":[]},{"index":6,"box":{"left":388,"top":74,"width":37,"height":54},"aHash64":"000000ffdfcee7c3","dHash64":"e7276915cfe1f2f9","pHash64":"7d0067d98c837d3c","autoDetected":false,"candidates":[]},{"index":7,"box":{"left":426,"top":74,"width":37,"height":54},"aHash64":"000000ff7ffffffe","dHash64":"0880275c1913160d","pHash64":"063959a6cdba750b","autoDetected":false,"candidates":[]},{"index":8,"box":{"left":464,"top":74,"width":37,"height":54},"aHash64":"000000ffff7fff1f","dHash64":"98e472961c46a349","pHash64":"364b34d3adf20966","autoDetected":false,"candidates":[]},{"index":9,"box":{"left":502,"top":74,"width":37,"height":54},"aHash64":"000000ffffbdffff","dHash64":"4b457621b48e8737","pHash64":"1b64130ae79d6a6b","autoDetected":false,"candidates":[]}],"adjacentDistances":[32,13,20,16,10,16,12,6,6],"groups":[{"startSlot":0,"span":1,"aHash64":"c190c087878785c7","dHash64":"76d9edf2f2f2f2f0","pHash64":"2a4c6b2aa272f9ea","autoDetected":false,"candidates":[{"itemId":157,"name":"Clamera","score":40},{"itemId":57,"name":"Battle Drone","score":39},{"itemId":234,"name":"Dock Lines","score":39},{"itemId":47,"name":"Banu Leaves","score":38},{"itemId":127,"name":"Captain's Wheel","score":38}],"bestScore":40,"secondScore":39,"bestMargin":1,"ambiguous":true},{"startSlot":1,"span":4,"aHash64":"80000002ffe7e6b6","dHash64":"df1d9e553131b193","pHash64":"67185ee19e704a5e","autoDetected":false,"candidates":[{"itemId":50,"name":"Barbed Wire","score":40},{"itemId":128,"name":"Caracara","score":40},{"itemId":147,"name":"Chocolate Bar","score":40},{"itemId":295,"name":"Floor Spike","score":40},{"itemId":78,"name":"Blender","score":39}],"bestScore":40,"secondScore":40,"bestMargin":0,"ambiguous":true},{"startSlot":5,"span":4,"aHash64":"000000ffffedffed","dHash64":"f1f8fed474666666","pHash64":"780f7bf0ed864154","autoDetected":false,"candidates":[{"itemId":272,"name":"Feather","score":40},{"itemId":21,"name":"Apothecary","score":39},{"itemId":40,"name":"Bag of Jewels","score":39},{"itemId":49,"name":"Barbed Claws","score":39}],"bestScore":40,"secondScore":39,"bestMargin":1,"ambiguous":true},{"startSlot":9,"span":1,"aHash64":"000000ffffbdffff","dHash64":"4b457621b48e8737","pHash64":"1b64130ae79d6a6b","autoDetected":false,"candidates":[{"itemId":7,"name":"Agility Boots","score":41},{"itemId":185,"name":"Cooling Fan","score":41},{"itemId":295,"name":"Floor Spike","score":41},{"itemId":40,"name":"Bag of Jewels","score":40}],"bestScore":41,"secondScore":41,"bestMargin":0,"ambiguous":true}],"groupMergeMaxAdjDist":20,"matchingEnv":"1","matchingEnabled":true,"itemCount":500,"hashedItemCount":300}